snakepie/__init__.py
snakepie-0.0.1.dist-info/METADATA
snakepie-0.0.1.dist-info/WHEEL
snakepie-0.0.1.dist-info/top_level.txt
snakepie-0.0.1.dist-info/RECORD
