Metadata-Version: 2.1
Name: snakepie
Version: 0.0.1
Summary: rapid api development framework in python
Home-page: https://snakepie.com
Author: oxbits
Author-email: alex@oxbits.com
License: UNKNOWN
Platform: UNKNOWN
